[
  {
    "id": 1,
    "name": "Rick Sanchez",
    "status": "Alive",
    "species": "Human",
    "type": "",
    "gender": "Male",
    "origin": {
      "name": "Earth (C-137)",
      "url": "https://rickandmortyapi.com/api/location/1"
    },
    "location": {
      "name": "Earth (Replacement Dimension)",
      "url": "https://rickandmortyapi.com/api/location/20"
    },
    "image": "https://rickandmortyapi.com/api/character/avatar/1.jpeg",
    "episode": [
      "https://rickandmortyapi.com/api/episode/1",
      "https://rickandmortyapi.com/api/episode/2",
      "https://rickandmortyapi.com/api/episode/3",
      "https://rickandmortyapi.com/api/episode/4",
      "https://rickandmortyapi.com/api/episode/5",
      "https://rickandmortyapi.com/api/episode/6",
      "https://rickandmortyapi.com/api/episode/7",
      "https://rickandmortyapi.com/api/episode/8",
      "https://rickandmortyapi.com/api/episode/9",
      "https://rickandmortyapi.com/api/episode/10",
      "https://rickandmortyapi.com/api/episode/11",
      "https://rickandmortyapi.com/api/episode/12",
      "https://rickandmortyapi.com/api/episode/13",
      "https://rickandmortyapi.com/api/episode/14",
      "https://rickandmortyapi.com/api/episode/15",
      "https://rickandmortyapi.com/api/episode/16",
      "https://rickandmortyapi.com/api/episode/17",
      "https://rickandmortyapi.com/api/episode/18",
      "https://rickandmortyapi.com/api/episode/19",
      "https://rickandmortyapi.com/api/episode/20",
      "https://rickandmortyapi.com/api/episode/21",
      "https://rickandmortyapi.com/api/episode/22",
      "https://rickandmortyapi.com/api/episode/23",
      "https://rickandmortyapi.com/api/episode/24",
      "https://rickandmortyapi.com/api/episode/25",
      "https://rickandmortyapi.com/api/episode/26",
      "https://rickandmortyapi.com/api/episode/27",
      "https://rickandmortyapi.com/api/episode/28",
      "https://rickandmortyapi.com/api/episode/29",
      "https://rickandmortyapi.com/api/episode/30",
      "https://rickandmortyapi.com/api/episode/31"
    ],
    "url": "https://rickandmortyapi.com/api/character/1",
    "created": "2017-11-04T18:48:46.250Z"
  },
  {
    "id": 2,
    "name": "Morty Smith",
    "status": "Alive",
    "species": "Human",
    "type": "",
    "gender": "Male",
    "origin": {
      "name": "Earth (C-137)",
      "url": "https://rickandmortyapi.com/api/location/1"
    },
    "location": {
      "name": "Earth (Replacement Dimension)",
      "url": "https://rickandmortyapi.com/api/location/20"
    },
    "image": "https://rickandmortyapi.com/api/character/avatar/2.jpeg",
    "episode": [
      "https://rickandmortyapi.com/api/episode/1",
      "https://rickandmortyapi.com/api/episode/2",
      "https://rickandmortyapi.com/api/episode/3",
      "https://rickandmortyapi.com/api/episode/4",
      "https://rickandmortyapi.com/api/episode/5",
      "https://rickandmortyapi.com/api/episode/6",
      "https://rickandmortyapi.com/api/episode/7",
      "https://rickandmortyapi.com/api/episode/8",
      "https://rickandmortyapi.com/api/episode/9",
      "https://rickandmortyapi.com/api/episode/10",
      "https://rickandmortyapi.com/api/episode/11",
      "https://rickandmortyapi.com/api/episode/12",
      "https://rickandmortyapi.com/api/episode/13",
      "https://rickandmortyapi.com/api/episode/14",
      "https://rickandmortyapi.com/api/episode/15",
      "https://rickandmortyapi.com/api/episode/16",
      "https://rickandmortyapi.com/api/episode/17",
      "https://rickandmortyapi.com/api/episode/18",
      "https://rickandmortyapi.com/api/episode/19",
      "https://rickandmortyapi.com/api/episode/20",
      "https://rickandmortyapi.com/api/episode/21",
      "https://rickandmortyapi.com/api/episode/22",
      "https://rickandmortyapi.com/api/episode/23",
      "https://rickandmortyapi.com/api/episode/24",
      "https://rickandmortyapi.com/api/episode/25",
      "https://rickandmortyapi.com/api/episode/26",
      "https://rickandmortyapi.com/api/episode/27",
      "https://rickandmortyapi.com/api/episode/28",
      "https://rickandmortyapi.com/api/episode/29",
      "https://rickandmortyapi.com/api/episode/30",
      "https://rickandmortyapi.com/api/episode/31"
    ],
    "url": "https://rickandmortyapi.com/api/character/2",
    "created": "2017-11-04T18:50:21.651Z"
  },
  {
    "id": 35,
    "name": "Bepisian",
    "status": "Alive",
    "species": "Alien",
    "type": "Bepisian",
    "gender": "unknown",
    "origin": {
      "name": "Bepis 9",
      "url": "https://rickandmortyapi.com/api/location/11"
    },
    "location": {
      "name": "Bepis 9",
      "url": "https://rickandmortyapi.com/api/location/11"
    },
    "image": "https://rickandmortyapi.com/api/character/avatar/35.jpeg",
    "episode": [
      "https://rickandmortyapi.com/api/episode/1",
      "https://rickandmortyapi.com/api/episode/11",
      "https://rickandmortyapi.com/api/episode/19",
      "https://rickandmortyapi.com/api/episode/25"
    ],
    "url": "https://rickandmortyapi.com/api/character/35",
    "created": "2017-11-05T09:27:38.491Z"
  },
  {
    "id": 38,
    "name": "Beth Smith",
    "status": "Alive",
    "species": "Human",
    "type": "",
    "gender": "Female",
    "origin": {
      "name": "Earth (C-137)",
      "url": "https://rickandmortyapi.com/api/location/1"
    },
    "location": {
      "name": "Earth (C-137)",
      "url": "https://rickandmortyapi.com/api/location/1"
    },
    "image": "https://rickandmortyapi.com/api/character/avatar/38.jpeg",
    "episode": [
      "https://rickandmortyapi.com/api/episode/1",
      "https://rickandmortyapi.com/api/episode/2",
      "https://rickandmortyapi.com/api/episode/3",
      "https://rickandmortyapi.com/api/episode/4",
      "https://rickandmortyapi.com/api/episode/5",
      "https://rickandmortyapi.com/api/episode/6",
      "https://rickandmortyapi.com/api/episode/22"
    ],
    "url": "https://rickandmortyapi.com/api/character/38",
    "created": "2017-11-05T09:48:44.230Z"
  },
  {
    "id": 43,
    "name": "Big Morty",
    "status": "Dead",
    "species": "Human",
    "type": "",
    "gender": "Male",
    "origin": {
      "name": "unknown",
      "url": ""
    },
    "location": {
      "name": "Citadel of Ricks",
      "url": "https://rickandmortyapi.com/api/location/3"
    },
    "image": "https://rickandmortyapi.com/api/character/avatar/43.jpeg",
    "episode": ["https://rickandmortyapi.com/api/episode/28"],
    "url": "https://rickandmortyapi.com/api/character/43",
    "created": "2017-11-05T10:17:04.997Z"
  },
  {
    "id": 62,
    "name": "Canklanker Thom",
    "status": "Dead",
    "species": "Alien",
    "type": "Gromflomite",
    "gender": "Male",
    "origin": {
      "name": "Gromflom Prime",
      "url": "https://rickandmortyapi.com/api/location/19"
    },
    "location": {
      "name": "unknown",
      "url": ""
    },
    "image": "https://rickandmortyapi.com/api/character/avatar/62.jpeg",
    "episode": ["https://rickandmortyapi.com/api/episode/1"],
    "url": "https://rickandmortyapi.com/api/character/62",
    "created": "2017-11-05T12:06:23.217Z"
  },
  {
    "id": 92,
    "name": "Davin",
    "status": "Dead",
    "species": "Human",
    "type": "",
    "gender": "Male",
    "origin": {
      "name": "Earth (C-137)",
      "url": "https://rickandmortyapi.com/api/location/1"
    },
    "location": {
      "name": "Earth (C-137)",
      "url": "https://rickandmortyapi.com/api/location/1"
    },
    "image": "https://rickandmortyapi.com/api/character/avatar/92.jpeg",
    "episode": [
      "https://rickandmortyapi.com/api/episode/1",
      "https://rickandmortyapi.com/api/episode/6"
    ],
    "url": "https://rickandmortyapi.com/api/character/92",
    "created": "2017-12-01T11:20:51.247Z"
  },
  {
    "id": 127,
    "name": "Frank Palicky",
    "status": "Dead",
    "species": "Human",
    "type": "",
    "gender": "Male",
    "origin": {
      "name": "Earth (C-137)",
      "url": "https://rickandmortyapi.com/api/location/1"
    },
    "location": {
      "name": "Earth (C-137)",
      "url": "https://rickandmortyapi.com/api/location/1"
    },
    "image": "https://rickandmortyapi.com/api/character/avatar/127.jpeg",
    "episode": ["https://rickandmortyapi.com/api/episode/1"],
    "url": "https://rickandmortyapi.com/api/character/127",
    "created": "2017-12-26T19:22:48.474Z"
  },
  {
    "id": 144,
    "name": "Glenn",
    "status": "Dead",
    "species": "Alien",
    "type": "Gromflomite",
    "gender": "Male",
    "origin": {
      "name": "unknown",
      "url": ""
    },
    "location": {
      "name": "Interdimensional Customs",
      "url": "https://rickandmortyapi.com/api/location/38"
    },
    "image": "https://rickandmortyapi.com/api/character/avatar/144.jpeg",
    "episode": ["https://rickandmortyapi.com/api/episode/1"],
    "url": "https://rickandmortyapi.com/api/character/144",
    "created": "2017-12-29T10:37:48.319Z"
  },
  {
    "id": 158,
    "name": "Hookah Alien",
    "status": "Alive",
    "species": "Alien",
    "type": "Tuskfish",
    "gender": "unknown",
    "origin": {
      "name": "unknown",
      "url": ""
    },
    "location": {
      "name": "Interdimensional Customs",
      "url": "https://rickandmortyapi.com/api/location/38"
    },
    "image": "https://rickandmortyapi.com/api/character/avatar/158.jpeg",
    "episode": ["https://rickandmortyapi.com/api/episode/1"],
    "url": "https://rickandmortyapi.com/api/character/158",
    "created": "2017-12-29T15:53:48.952Z"
  },
  {
    "id": 175,
    "name": "Jerry Smith",
    "status": "Alive",
    "species": "Human",
    "type": "",
    "gender": "Male",
    "origin": {
      "name": "Earth (C-137)",
      "url": "https://rickandmortyapi.com/api/location/1"
    },
    "location": {
      "name": "Earth (C-137)",
      "url": "https://rickandmortyapi.com/api/location/1"
    },
    "image": "https://rickandmortyapi.com/api/character/avatar/175.jpeg",
    "episode": [
      "https://rickandmortyapi.com/api/episode/1",
      "https://rickandmortyapi.com/api/episode/2",
      "https://rickandmortyapi.com/api/episode/3",
      "https://rickandmortyapi.com/api/episode/4",
      "https://rickandmortyapi.com/api/episode/5",
      "https://rickandmortyapi.com/api/episode/6",
      "https://rickandmortyapi.com/api/episode/22"
    ],
    "url": "https://rickandmortyapi.com/api/character/175",
    "created": "2017-12-29T18:07:17.610Z"
  },
  {
    "id": 179,
    "name": "Jessica",
    "status": "Alive",
    "species": "Cronenberg",
    "type": "",
    "gender": "Female",
    "origin": {
      "name": "Earth (C-137)",
      "url": "https://rickandmortyapi.com/api/location/1"
    },
    "location": {
      "name": "Earth (C-137)",
      "url": "https://rickandmortyapi.com/api/location/1"
    },
    "image": "https://rickandmortyapi.com/api/character/avatar/179.jpeg",
    "episode": [
      "https://rickandmortyapi.com/api/episode/1",
      "https://rickandmortyapi.com/api/episode/4",
      "https://rickandmortyapi.com/api/episode/6"
    ],
    "url": "https://rickandmortyapi.com/api/character/179",
    "created": "2017-12-29T18:34:37.806Z"
  },
  {
    "id": 181,
    "name": "Jessica's Friend",
    "status": "Alive",
    "species": "Human",
    "type": "",
    "gender": "Female",
    "origin": {
      "name": "Earth (C-137)",
      "url": "https://rickandmortyapi.com/api/location/1"
    },
    "location": {
      "name": "Earth (Replacement Dimension)",
      "url": "https://rickandmortyapi.com/api/location/20"
    },
    "image": "https://rickandmortyapi.com/api/character/avatar/181.jpeg",
    "episode": [
      "https://rickandmortyapi.com/api/episode/1",
      "https://rickandmortyapi.com/api/episode/4",
      "https://rickandmortyapi.com/api/episode/6",
      "https://rickandmortyapi.com/api/episode/11",
      "https://rickandmortyapi.com/api/episode/17",
      "https://rickandmortyapi.com/api/episode/18",
      "https://rickandmortyapi.com/api/episode/25",
      "https://rickandmortyapi.com/api/episode/27"
    ],
    "url": "https://rickandmortyapi.com/api/character/181",
    "created": "2017-12-29T18:47:23.345Z"
  },
  {
    "id": 239,
    "name": "Mr. Goldenfold",
    "status": "Alive",
    "species": "Cronenberg",
    "type": "",
    "gender": "Male",
    "origin": {
      "name": "Earth (C-137)",
      "url": "https://rickandmortyapi.com/api/location/1"
    },
    "location": {
      "name": "Earth (C-137)",
      "url": "https://rickandmortyapi.com/api/location/1"
    },
    "image": "https://rickandmortyapi.com/api/character/avatar/239.jpeg",
    "episode": [
      "https://rickandmortyapi.com/api/episode/1",
      "https://rickandmortyapi.com/api/episode/2",
      "https://rickandmortyapi.com/api/episode/4",
      "https://rickandmortyapi.com/api/episode/6"
    ],
    "url": "https://rickandmortyapi.com/api/character/239",
    "created": "2017-12-30T17:42:11.894Z"
  },
  {
    "id": 249,
    "name": "Mrs. Sanchez",
    "status": "unknown",
    "species": "Human",
    "type": "",
    "gender": "Female",
    "origin": {
      "name": "unknown",
      "url": ""
    },
    "location": {
      "name": "unknown",
      "url": ""
    },
    "image": "https://rickandmortyapi.com/api/character/avatar/249.jpeg",
    "episode": [
      "https://rickandmortyapi.com/api/episode/1",
      "https://rickandmortyapi.com/api/episode/6",
      "https://rickandmortyapi.com/api/episode/14",
      "https://rickandmortyapi.com/api/episode/30"
    ],
    "url": "https://rickandmortyapi.com/api/character/249",
    "created": "2017-12-30T18:18:10.965Z"
  },
  {
    "id": 271,
    "name": "Principal Vagina",
    "status": "Alive",
    "species": "Cronenberg",
    "type": "",
    "gender": "Male",
    "origin": {
      "name": "Earth (C-137)",
      "url": "https://rickandmortyapi.com/api/location/1"
    },
    "location": {
      "name": "Earth (C-137)",
      "url": "https://rickandmortyapi.com/api/location/1"
    },
    "image": "https://rickandmortyapi.com/api/character/avatar/271.jpeg",
    "episode": [
      "https://rickandmortyapi.com/api/episode/1",
      "https://rickandmortyapi.com/api/episode/5",
      "https://rickandmortyapi.com/api/episode/6"
    ],
    "url": "https://rickandmortyapi.com/api/character/271",
    "created": "2017-12-31T14:08:43.602Z"
  },
  {
    "id": 338,
    "name": "Summer Smith",
    "status": "Alive",
    "species": "Human",
    "type": "",
    "gender": "Female",
    "origin": {
      "name": "Earth (C-137)",
      "url": "https://rickandmortyapi.com/api/location/1"
    },
    "location": {
      "name": "Earth (C-137)",
      "url": "https://rickandmortyapi.com/api/location/1"
    },
    "image": "https://rickandmortyapi.com/api/character/avatar/338.jpeg",
    "episode": [
      "https://rickandmortyapi.com/api/episode/1",
      "https://rickandmortyapi.com/api/episode/2",
      "https://rickandmortyapi.com/api/episode/3",
      "https://rickandmortyapi.com/api/episode/4",
      "https://rickandmortyapi.com/api/episode/5",
      "https://rickandmortyapi.com/api/episode/6",
      "https://rickandmortyapi.com/api/episode/22"
    ],
    "url": "https://rickandmortyapi.com/api/character/338",
    "created": "2018-01-10T16:55:03.390Z"
  },
  {
    "id": 394,
    "name": "Davin",
    "status": "Dead",
    "species": "Cronenberg",
    "type": "",
    "gender": "Male",
    "origin": {
      "name": "Earth (C-137)",
      "url": "https://rickandmortyapi.com/api/location/1"
    },
    "location": {
      "name": "Earth (C-137)",
      "url": "https://rickandmortyapi.com/api/location/1"
    },
    "image": "https://rickandmortyapi.com/api/character/avatar/394.jpeg",
    "episode": [
      "https://rickandmortyapi.com/api/episode/1",
      "https://rickandmortyapi.com/api/episode/6"
    ],
    "url": "https://rickandmortyapi.com/api/character/394",
    "created": "2018-01-20T19:48:42.201Z"
  },
  {
    "id": 395,
    "name": "Greebybobe",
    "status": "Alive",
    "species": "Alien",
    "type": "Greebybobe",
    "gender": "unknown",
    "origin": {
      "name": "Girvonesk",
      "url": "https://rickandmortyapi.com/api/location/68"
    },
    "location": {
      "name": "Worldender's lair",
      "url": "https://rickandmortyapi.com/api/location/4"
    },
    "image": "https://rickandmortyapi.com/api/character/avatar/395.jpeg",
    "episode": [
      "https://rickandmortyapi.com/api/episode/1",
      "https://rickandmortyapi.com/api/episode/11",
      "https://rickandmortyapi.com/api/episode/16",
      "https://rickandmortyapi.com/api/episode/25"
    ],
    "url": "https://rickandmortyapi.com/api/character/395",
    "created": "2018-04-15T16:46:31.715Z"
  }
]
